nowsync
