Metadata-Version: 1.0
Name: nowsync
Version: 0.3b.dev26
Summary: A set of tool for synchronizing local modification to remoteWSGI server, makes life of designer easier
Home-page: https://bitbucket.org/victorlin/nowsync
Author: Victor Lin
Author-email: bornstub@gmail.com
License: MIT
Platform: UNKNOWN
